danker/__init__.py
danker/__main__.py
danker/danker.py
danker-0.8.1.dist-info/LICENSE
danker-0.8.1.dist-info/METADATA
danker-0.8.1.dist-info/WHEEL
danker-0.8.1.dist-info/top_level.txt
danker-0.8.1.dist-info/RECORD
