Metadata-Version: 2.1
Name: danker
Version: 0.8.1
Summary: Compute PageRank on large graphs with off-the-shelf hardware.
Home-page: https://github.com/athalhammer/danker
Author: Andreas Thalhammer
Author-email: andreas@thalhammer.bayern
Classifier: Programming Language :: Python :: 3.8
Classifier: Programming Language :: Python :: 3.9
Classifier: License :: OSI Approved :: GNU General Public License v3 (GPLv3)
Classifier: Operating System :: OS Independent
Classifier: Topic :: Scientific/Engineering :: Information Analysis
Requires-Python: >=3.8
License-File: LICENSE
